{
    "municipio": "",
    "codigo_ibge": "",
    "fonte": "SEPLAN-TO - Perfil Socioeconômico 2024 (8ª Edição)",
    "versao_extrator": "9.0",
    "indicadores": {
        "pop_1991": 13933.0,
        "pop_2000": 6815.0,
        "pop_2010": 7104.0,
        "pop_2022": 6819.0,
        "densidade_1991": 4.6,
        "densidade_2000": 2.2,
        "densidade_2010": 2.3,
        "densidade_2022": 2.2,
        "taxa_urbanizacao_1991": 22.8,
        "taxa_urbanizacao_2000": 53.2,
        "taxa_urbanizacao_2010": 60.1,
        "taxa_urbanizacao_2022": 59.9,
        "idhm_1991": 0.311,
        "idhm_2000": 0.426,
        "idhm_2010": 0.612,
        "idhm_longevidade_1991": 0.613,
        "idhm_longevidade_2000": 0.662,
        "idhm_longevidade_2010": 0.798,
        "idhm_educacao_1991": 0.111,
        "idhm_educacao_2000": 0.218,
        "idhm_educacao_2010": 0.491,
        "idhm_renda_1991": 0.44,
        "idhm_renda_2000": 0.536,
        "idhm_renda_2010": 0.585,
        "pib_total_2017": 98358.0,
        "pib_per_capita_2017": 9940.87,
        "pib_total_2018": 99047.0,
        "pib_per_capita_2018": 10919.91,
        "pib_total_2019": 106507.0,
        "pib_per_capita_2019": 11702.49,
        "pib_total_2020": 119953.0,
        "pib_per_capita_2020": 12486.84,
        "pib_total_2021": 186260.0,
        "pib_per_capita_2021": 14240.76,
        "vab_agropecuaria_2017": 11600.0,
        "vab_industria_2017": 1530.0,
        "vab_servicos_2017": 34700.0,
        "vab_agropecuaria_2018": 12029.0,
        "vab_industria_2018": 3744.0,
        "vab_servicos_2018": 37525.0,
        "vab_agropecuaria_2019": 12856.0,
        "vab_industria_2019": 2950.0,
        "vab_servicos_2019": 41445.0,
        "vab_agropecuaria_2020": 15753.0,
        "vab_industria_2020": 2680.0,
        "vab_servicos_2020": 42660.0,
        "vab_agropecuaria_2021": 22952.0,
        "vab_industria_2021": 2905.0,
        "vab_servicos_2021": 45036.0,
        "emprego_formal_estoque_2020": 1.0,
        "emprego_formal_estoque_2021": 182.0,
        "emprego_formal_estoque_2022": 204.0,
        "emprego_formal_estoque_2023": 225.0,
        "taxa_alfabetizacao_2000": 72.1,
        "taxa_alfabetizacao_2010": 81.8,
        "taxa_alfabetizacao_2022": 86.6,
        "agua_rede_geral_1991": 3.0,
        "agua_rede_geral_2000": 221.0,
        "agua_rede_geral_2010": 930.0,
        "agua_rede_geral_2022": 1374.0,
        "esgoto_rede_geral_1991": 31.0,
        "esgoto_rede_geral_2000": 1.0,
        "esgoto_rede_geral_2010": 350.0,
        "esgoto_rede_geral_2022": 736.0,
        "lixo_coletado_1991": 190.0,
        "lixo_coletado_2000": 759.0,
        "lixo_coletado_2010": 1230.0,
        "lixo_coletado_2022": 1557.0,
        "estabelecimentos_ubs_2023": 2.0,
        "estabelecimentos_hospital_2023": 1.0,
        "transferencias_total_2019": 10051912.0,
        "transferencias_total_2020": 9896234.0,
        "transferencias_total_2021": 12618705.0,
        "transferencias_total_2022": 15285985.0,
        "transferencias_total_2023": 16715942.0,
        "fpm_2019": 6047595.0,
        "fpm_2020": 5784934.0,
        "fpm_2021": 7694030.0,
        "fpm_2022": 9710773.0,
        "fpm_2023": 10048809.0,
        "itr_2019": 144653.0,
        "itr_2020": 146597.0,
        "itr_2021": 96869.0,
        "itr_2022": 142226.0,
        "itr_2023": 149611.0,
        "fundeb_2019": 3838104.0,
        "fundeb_2020": 3946649.0,
        "fundeb_2021": 4816003.0,
        "fundeb_2022": 5414729.0,
        "fundeb_2023": 6513875.0,
        "icms_2019": 3979793.0,
        "ipva_2019": 248525.0,
        "icms_2020": 3265355.0,
        "ipva_2020": 315709.0,
        "icms_2021": 7278719.0,
        "ipva_2021": 331691.0,
        "icms_2022": 7185783.0,
        "ipva_2022": 405155.0,
        "icms_2023": 6281357.0,
        "ipva_2023": 459685.0
    }
}