{
    "municipio": "",
    "codigo_ibge": "",
    "fonte": "SEPLAN-TO - Perfil Socioeconômico 2024 (8ª Edição)",
    "versao_extrator": "9.0",
    "indicadores": {
        "pop_1991": 2333.0,
        "pop_2000": 3332.0,
        "pop_2010": 4352.0,
        "pop_2022": 4615.0,
        "densidade_1991": 1.1,
        "densidade_2000": 1.6,
        "densidade_2010": 2.1,
        "densidade_2022": 2.2,
        "taxa_urbanizacao_1991": 59.8,
        "taxa_urbanizacao_2000": 59.1,
        "taxa_urbanizacao_2010": 54.8,
        "taxa_urbanizacao_2022": 55.9,
        "idhm_1991": 0.321,
        "idhm_2000": 0.497,
        "idhm_2010": 0.631,
        "idhm_longevidade_1991": 0.541,
        "idhm_longevidade_2000": 0.656,
        "idhm_longevidade_2010": 0.792,
        "idhm_educacao_1991": 0.135,
        "idhm_educacao_2000": 0.311,
        "idhm_educacao_2010": 0.504,
        "idhm_renda_1991": 0.454,
        "idhm_renda_2000": 0.6,
        "idhm_renda_2010": 0.63,
        "pib_total_2017": 120349.0,
        "pib_per_capita_2017": 48304.22,
        "pib_total_2018": 126046.0,
        "pib_per_capita_2018": 51439.31,
        "pib_total_2019": 146974.0,
        "pib_per_capita_2019": 69269.29,
        "pib_total_2020": 210074.0,
        "pib_per_capita_2020": 83358.45,
        "pib_total_2021": 252331.0,
        "pib_per_capita_2021": 91006.23,
        "vab_agropecuaria_2017": 85865.0,
        "vab_industria_2017": 3623.0,
        "vab_servicos_2017": 18624.0,
        "vab_agropecuaria_2018": 92993.0,
        "vab_industria_2018": 4167.0,
        "vab_servicos_2018": 19666.0,
        "vab_agropecuaria_2019": 132369.0,
        "vab_industria_2019": 5059.0,
        "vab_servicos_2019": 21164.0,
        "vab_agropecuaria_2020": 170522.0,
        "vab_industria_2020": 5114.0,
        "vab_servicos_2020": 22947.0,
        "vab_agropecuaria_2021": 192768.0,
        "vab_industria_2021": 6237.0,
        "vab_servicos_2021": 26142.0,
        "emprego_formal_estoque_2020": 1.0,
        "emprego_formal_estoque_2021": 318.0,
        "emprego_formal_estoque_2022": 374.0,
        "emprego_formal_estoque_2023": 621.0,
        "taxa_alfabetizacao_2000": 85.4,
        "taxa_alfabetizacao_2010": 82.0,
        "taxa_alfabetizacao_2022": 91.4,
        "agua_rede_geral_1991": 3.0,
        "agua_rede_geral_2000": 461.0,
        "agua_rede_geral_2010": 846.0,
        "agua_rede_geral_2022": 1036.0,
        "estabelecimentos_ubs_2023": 1.0,
        "estabelecimentos_hospital_2023": 1.0,
        "transferencias_total_2019": 10176926.0,
        "transferencias_total_2020": 10596232.0,
        "transferencias_total_2021": 14127664.0,
        "transferencias_total_2022": 16610269.0,
        "transferencias_total_2023": 19895437.0,
        "fpm_2019": 6047595.0,
        "fpm_2020": 5784934.0,
        "fpm_2021": 7694030.0,
        "fpm_2022": 9710773.0,
        "fpm_2023": 10048809.0,
        "itr_2019": 285120.0,
        "itr_2020": 697374.0,
        "itr_2021": 1126589.0,
        "itr_2022": 1155014.0,
        "itr_2023": 2421323.0,
        "fundeb_2019": 3825919.0,
        "fundeb_2020": 4098519.0,
        "fundeb_2021": 5296916.0,
        "fundeb_2022": 5728737.0,
        "fundeb_2023": 7422155.0,
        "icms_2019": 3103880.0,
        "ipva_2019": 227710.0,
        "icms_2020": 3728283.0,
        "ipva_2020": 214027.0,
        "icms_2021": 6246634.0,
        "ipva_2021": 266378.0,
        "icms_2022": 6387793.0,
        "ipva_2022": 339297.0,
        "icms_2023": 6074762.0,
        "ipva_2023": 417795.0
    }
}