{
    "municipio": "",
    "codigo_ibge": "",
    "fonte": "SEPLAN-TO - Perfil Socioeconômico 2024 (8ª Edição)",
    "versao_extrator": "9.0",
    "indicadores": {
        "idhm_1991": 0.331,
        "idhm_2000": 0.386,
        "idhm_2010": 0.596,
        "idhm_longevidade_1991": 0.523,
        "idhm_longevidade_2000": 0.655,
        "idhm_longevidade_2010": 0.745,
        "idhm_educacao_1991": 0.139,
        "idhm_educacao_2000": 0.173,
        "idhm_educacao_2010": 0.524,
        "idhm_renda_1991": 0.5,
        "idhm_renda_2000": 0.509,
        "idhm_renda_2010": 0.543,
        "pib_total_2017": 43100.0,
        "pib_per_capita_2017": 12555.5,
        "pib_total_2018": 43009.0,
        "pib_per_capita_2018": 18838.02,
        "pib_total_2019": 47556.0,
        "pib_per_capita_2019": 16945.75,
        "pib_total_2020": 57096.0,
        "pib_per_capita_2020": 20422.68,
        "pib_total_2021": 69465.0,
        "pib_per_capita_2021": 26722.15,
        "vab_agropecuaria_2017": 17325.0,
        "vab_industria_2017": 9413.0,
        "vab_servicos_2017": 51552.0,
        "vab_agropecuaria_2018": 18153.0,
        "vab_industria_2018": 41953.0,
        "vab_servicos_2018": 55690.0,
        "vab_agropecuaria_2019": 19916.0,
        "vab_industria_2019": 28806.0,
        "vab_servicos_2019": 58840.0,
        "vab_agropecuaria_2020": 29835.0,
        "vab_industria_2020": 43031.0,
        "vab_servicos_2020": 60823.0,
        "vab_agropecuaria_2021": 50943.0,
        "vab_industria_2021": 57012.0,
        "vab_servicos_2021": 67661.0,
        "emprego_formal_estoque_2020": 1.0,
        "emprego_formal_estoque_2021": 233.0,
        "emprego_formal_estoque_2022": 230.0,
        "emprego_formal_estoque_2023": 259.0,
        "taxa_alfabetizacao_2000": 64.8,
        "taxa_alfabetizacao_2010": 76.1,
        "taxa_alfabetizacao_2022": 86.2,
        "agua_rede_geral_1991": 3.0,
        "agua_rede_geral_2000": 328.0,
        "agua_rede_geral_2010": 504.0,
        "agua_rede_geral_2022": 678.0,
        "esgoto_rede_geral_1991": 31.0,
        "esgoto_rede_geral_2000": 1.0,
        "esgoto_rede_geral_2010": 2.0,
        "esgoto_rede_geral_2022": 1.0,
        "estabelecimentos_ubs_2023": 1.0,
        "transferencias_total_2019": 8341754.0,
        "transferencias_total_2020": 8217433.0,
        "transferencias_total_2021": 10648526.0,
        "transferencias_total_2022": 12887135.0,
        "transferencias_total_2023": 13708418.0,
        "fpm_2019": 6047595.0,
        "fpm_2020": 5784934.0,
        "fpm_2021": 7694030.0,
        "fpm_2022": 9710773.0,
        "fpm_2023": 10048809.0,
        "itr_2019": 83473.0,
        "itr_2020": 100066.0,
        "itr_2021": 119497.0,
        "itr_2022": 147411.0,
        "itr_2023": 195579.0,
        "fundeb_2019": 2194586.0,
        "fundeb_2020": 2318904.0,
        "fundeb_2021": 2826125.0,
        "fundeb_2022": 3015183.0,
        "fundeb_2023": 3461277.0,
        "icms_2019": 1450055.0,
        "ipva_2019": 69318.0,
        "icms_2020": 1823958.0,
        "ipva_2020": 76536.0,
        "icms_2021": 2377485.0,
        "ipva_2021": 109637.0,
        "icms_2022": 2801140.0,
        "ipva_2022": 87928.0,
        "icms_2023": 2837419.0,
        "ipva_2023": 147750.0
    }
}